<?xml version="1.0" encoding="utf-8" ?>
<dwsync>
<file name="bootstrap-glyphicons.css" server="C:/xampp/htdocs/PROJETOS/layouts/" local="130197609701154976" remote="130197609700000000" Dst="1" />
<file name="bootstrap.css" server="C:/xampp/htdocs/PROJETOS/layouts/" local="130193560900000000" remote="130193560900000000" Dst="1" />
<file name="bootstrap.min.css" server="C:/xampp/htdocs/PROJETOS/layouts/" local="130193560900000000" remote="130193560900000000" Dst="1" />
<file name="carousel.css" server="C:/xampp/htdocs/PROJETOS/layouts/" local="130193560900000000" remote="130193560900000000" Dst="1" />
<file name="docs.css" server="C:/xampp/htdocs/PROJETOS/layouts/" local="130193538600000000" remote="130193538600000000" Dst="1" />
<file name="estilo.css" server="C:/xampp/htdocs/PROJETOS/layouts/" local="130195712173817044" remote="130195712170000000" Dst="1" />
<file name="sticky-footer-navbar.css" server="C:/xampp/htdocs/PROJETOS/layouts/" local="130193560900000000" remote="130193560900000000" Dst="1" />
<file name="bootstrap.css" server="ftp.prodapro.com.br/public_html/projeto/" local="130203702315592561" remote="130204682430000000" Dst="1" />
<file name="sticky-footer-navbar.css" server="ftp.prodapro.com.br/public_html/projeto/" local="130200082527351297" remote="130201972200000000" Dst="1" />
<file name="bootstrap-glyphicons.css" server="ftp.prodapro.com.br/public_html/projeto/" local="130200082532481590" remote="130201972150000000" Dst="1" />
<file name="bootstrap.min.css" server="ftp.prodapro.com.br/public_html/projeto/" local="130200082522681030" remote="130201972190000000" Dst="1" />
<file name="carousel.css" server="ftp.prodapro.com.br/public_html/projeto/" local="130200082524441131" remote="130201972190000000" Dst="1" />
<file name="docs.css" server="ftp.prodapro.com.br/public_html/projeto/" local="130200082532431588" remote="130201972200000000" Dst="1" />
<file name="estilo.css" server="ftp.prodapro.com.br/public_html/projeto/" local="130200082537331868" remote="130201972200000000" Dst="1" />
<file name="menuleft.css" server="ftp.prodapro.com.br/public_html/projeto/" local="130200116270521296" remote="130201972200000000" Dst="1" />
<file name="jquery-ui themes base images ui-bg_glass_55_fbf9ee_1x400.png at master · jquery jquery-ui · GitHub.htm" server="ftp.prodapro.com.br/public_html/projeto/" local="130202630485878277" remote="130204682440000000" Dst="1" />
<file name="jquery-ui.css" server="ftp.prodapro.com.br/public_html/projeto/" local="130204408976040720" remote="130204682600000000" Dst="1" />
<file name="bootstrap.css" server="ftp.prodapro.com/public_html/" local="130215894291668898" remote="130215894620000000" Dst="1" />
<file name="bootstrap-glyphicons.css" server="ftp.prodapro.com/public_html/" local="130200082532481590" remote="130215633430000000" Dst="1" />
<file name="bootstrap.min.css" server="ftp.prodapro.com/public_html/" local="130200082522681030" remote="130215633480000000" Dst="1" />
<file name="carousel.css" server="ftp.prodapro.com/public_html/" local="130200082524441131" remote="130215633480000000" Dst="1" />
<file name="docs.css" server="ftp.prodapro.com/public_html/" local="130200082532431588" remote="130215633480000000" Dst="1" />
<file name="estilo.css" server="ftp.prodapro.com/public_html/" local="130200082537331868" remote="130215633490000000" Dst="1" />
<file name="jquery-ui themes base images ui-bg_glass_55_fbf9ee_1x400.png at master · jquery jquery-ui · GitHub.htm" server="ftp.prodapro.com/public_html/" local="130202630485878277" remote="130215633490000000" Dst="1" />
<file name="jquery-ui.css" server="ftp.prodapro.com/public_html/" local="130204408976040720" remote="130215633680000000" Dst="1" />
<file name="menuleft.css" server="ftp.prodapro.com/public_html/" local="130200116270521296" remote="130215633710000000" Dst="1" />
<file name="sticky-footer-navbar.css" server="ftp.prodapro.com/public_html/" local="130200082527351297" remote="130215633710000000" Dst="1" />
<file name="app.v1.css" server="C:/xampp/htdocs/PROJETOS/NfeNotasDownload/simples/" local="130481813680000000" remote="130481813680000000" Dst="1" />
<file name="bootplus-responsive.css" server="C:/xampp/htdocs/PROJETOS/NfeNotasDownload/simples/" local="130292139520000000" remote="130292175520000000" Dst="1" />
<file name="bootplus.css" server="C:/xampp/htdocs/PROJETOS/NfeNotasDownload/simples/" local="130813779980000000" remote="130813779980000000" Dst="1" />
<file name="bootstrap-glyphicons.css" server="C:/xampp/htdocs/PROJETOS/NfeNotasDownload/simples/" local="130512821160000000" remote="130512821160000000" Dst="1" />
<file name="bootstrap-select.css" server="C:/xampp/htdocs/PROJETOS/NfeNotasDownload/simples/" local="130512821160000000" remote="130512821160000000" Dst="1" />
<file name="bootstrap-theme.min.css" server="C:/xampp/htdocs/PROJETOS/NfeNotasDownload/simples/" local="130512821160000000" remote="130512821160000000" Dst="1" />
<file name="bootstrap.css" server="C:/xampp/htdocs/PROJETOS/NfeNotasDownload/simples/" local="130619188460000000" remote="130619224460000000" Dst="1" />
<file name="bootstrap.min.css" server="C:/xampp/htdocs/PROJETOS/NfeNotasDownload/simples/" local="130512821160000000" remote="130512821160000000" Dst="1" />
<file name="carousel.css" server="C:/xampp/htdocs/PROJETOS/NfeNotasDownload/simples/" local="130512821160000000" remote="130512821160000000" Dst="1" />
<file name="chosen.css" server="C:/xampp/htdocs/PROJETOS/NfeNotasDownload/simples/" local="130512821160000000" remote="130512821160000000" Dst="1" />
<file name="dataTables.tableTools.css" server="C:/xampp/htdocs/PROJETOS/NfeNotasDownload/simples/" local="130482012800000000" remote="130482012800000000" Dst="1" />
<file name="datepicker3.css" server="C:/xampp/htdocs/PROJETOS/NfeNotasDownload/simples/" local="130345931280000000" remote="130345967280000000" Dst="1" />
<file name="docs.css" server="C:/xampp/htdocs/PROJETOS/NfeNotasDownload/simples/" local="130483472780000000" remote="130483472780000000" Dst="1" />
<file name="estilo.css" server="C:/xampp/htdocs/PROJETOS/NfeNotasDownload/simples/" local="130512821160000000" remote="130512821160000000" Dst="1" />
<file name="font-awesome-ie7.min.css" server="C:/xampp/htdocs/PROJETOS/NfeNotasDownload/simples/" local="130292139520000000" remote="130292175520000000" Dst="1" />
<file name="font-awesome.min.css" server="C:/xampp/htdocs/PROJETOS/NfeNotasDownload/simples/" local="130292139520000000" remote="130292175520000000" Dst="1" />
<file name="jquery-ui themes base images ui-bg_glass_55_fbf9ee_1x400.png at master · jquery jquery-ui · GitHub.htm" server="C:/xampp/htdocs/PROJETOS/NfeNotasDownload/simples/" local="130512821160000000" remote="130512821160000000" Dst="1" />
<file name="jquery-ui.css" server="C:/xampp/htdocs/PROJETOS/NfeNotasDownload/simples/" local="130495563960000000" remote="130495563960000000" Dst="1" />
<file name="jquery.dataTables.css" server="C:/xampp/htdocs/PROJETOS/NfeNotasDownload/simples/" local="130541616360000000" remote="130541616360000000" Dst="1" />
<file name="menuleft.css" server="C:/xampp/htdocs/PROJETOS/NfeNotasDownload/simples/" local="130512821140000000" remote="130512821140000000" Dst="1" />
<file name="menu_front.css" server="C:/xampp/htdocs/PROJETOS/NfeNotasDownload/simples/" local="131596450500000000" remote="131596486500000000" Dst="1" />
<file name="pnotify.custom.min.css" server="C:/xampp/htdocs/PROJETOS/NfeNotasDownload/simples/" local="130578691260000000" remote="130578691260000000" Dst="1" />
<file name="printproducao.css" server="C:/xampp/htdocs/PROJETOS/NfeNotasDownload/simples/" local="130559801460000000" remote="130559801460000000" Dst="1" />
<file name="selectric.css" server="C:/xampp/htdocs/PROJETOS/NfeNotasDownload/simples/" local="130548525280000000" remote="130548525280000000" Dst="1" />
<file name="sticky-footer-navbar.css" server="C:/xampp/htdocs/PROJETOS/NfeNotasDownload/simples/" local="130512821140000000" remote="130512821140000000" Dst="1" />
</dwsync>